README.rst
setup.cfg
setup.py
django_model_history2.egg-info/PKG-INFO
django_model_history2.egg-info/SOURCES.txt
django_model_history2.egg-info/dependency_links.txt
django_model_history2.egg-info/top_level.txt
model_history/__init__.py
model_history/admin.py
model_history/apps.py
model_history/decorators.py
model_history/models.py
model_history/settings.py
model_history/signals.py
model_history/utils.py
model_history/migrations/0001_initial.py
model_history/migrations/0002_history_status.py
model_history/migrations/0003_auto_20151116_1409.py
model_history/migrations/__init__.py