Metadata-Version: 1.1
Name: django-model-history2
Version: 0.9.3
Summary: Utility to track changes in object models
Home-page: https://github.com/shamanis/django-model-history2
Author: Petr Bondarenko
Author-email: mdma.zone@gmail.com
License: MIT
Keywords: models history revert objects
Platform: UNKNOWN
Classifier: Development Status :: 5 - Production/Stable
Classifier: Framework :: Django
Classifier: Intended Audience :: Developers
Classifier: License :: OSI Approved :: MIT License
Classifier: Operating System :: OS Independent
Classifier: Programming Language :: Python
Classifier: Topic :: Utilities
